WordToNum/__init__.py
WordToNum/word_to_num.py
WordToNum-0.0.4.dist-info/METADATA
WordToNum-0.0.4.dist-info/WHEEL
WordToNum-0.0.4.dist-info/top_level.txt
WordToNum-0.0.4.dist-info/RECORD
