Metadata-Version: 2.1
Name: WordToNum
Version: 0.0.4
Summary: Converts word in string to actual number
Home-page: https://github.com/ashyam95/WordToNum
Author: Ashyam Zubair
Author-email: ashyamzubair@gmail.com
License: UNKNOWN
Platform: UNKNOWN
Classifier: Programming Language :: Python :: 3
Classifier: License :: OSI Approved :: MIT License
Classifier: Operating System :: OS Independent
